excel2rdf/__init__.py
excel2rdf/cli.py
excel2rdf-0.1.12.dist-info/LICENSE
excel2rdf-0.1.12.dist-info/METADATA
excel2rdf-0.1.12.dist-info/WHEEL
excel2rdf-0.1.12.dist-info/entry_points.txt
excel2rdf-0.1.12.dist-info/top_level.txt
excel2rdf-0.1.12.dist-info/RECORD
